odoo/addons/l10n_us_account_routing/README.rst
odoo/addons/l10n_us_account_routing/__init__.py
odoo/addons/l10n_us_account_routing/__manifest__.py
odoo/addons/l10n_us_account_routing/i18n/l10n_us_account_routing.pot
odoo/addons/l10n_us_account_routing/models/__init__.py
odoo/addons/l10n_us_account_routing/models/res_bank.py
odoo/addons/l10n_us_account_routing/readme/CONTRIBUTORS.md
odoo/addons/l10n_us_account_routing/readme/DESCRIPTION.md
odoo/addons/l10n_us_account_routing/static/description/icon.png
odoo/addons/l10n_us_account_routing/static/description/index.html
odoo/addons/l10n_us_account_routing/tests/__init__.py
odoo/addons/l10n_us_account_routing/tests/test_routing_number_bank.py
odoo/addons/l10n_us_account_routing/views/res_bank.xml
odoo_addon_l10n_us_account_routing-18.0.1.0.0.2.dist-info/METADATA
odoo_addon_l10n_us_account_routing-18.0.1.0.0.2.dist-info/WHEEL
odoo_addon_l10n_us_account_routing-18.0.1.0.0.2.dist-info/top_level.txt
odoo_addon_l10n_us_account_routing-18.0.1.0.0.2.dist-info/RECORD
