Metadata-Version: 2.1
Name: odoo-addon-l10n_us_account_routing
Version: 18.0.1.0.0.2
Requires-Python: >=3.10
Requires-Dist: odoo==18.0.*
Requires-Dist: python-stdnum
Summary: Add the routing numbers to the banks
Home-page: https://github.com/OCA/l10n-usa
License: LGPL-3
Author: ForgeFlow, Odoo Community Association (OCA)
Author-email: support@odoo-community.org
Classifier: Programming Language :: Python
Classifier: Framework :: Odoo
Classifier: Framework :: Odoo :: 18.0
Classifier: License :: OSI Approved :: GNU Lesser General Public License v3 (LGPLv3)
